langgraph_checkpoint_dynamodb/__init__.py
langgraph_checkpoint_dynamodb/saver.py
langgraph_checkpoint_dynamodb/write.py
langgraph_checkpoint_dynamodb-0.1.0.dist-info/LICENSE
langgraph_checkpoint_dynamodb-0.1.0.dist-info/METADATA
langgraph_checkpoint_dynamodb-0.1.0.dist-info/WHEEL
langgraph_checkpoint_dynamodb-0.1.0.dist-info/top_level.txt
langgraph_checkpoint_dynamodb-0.1.0.dist-info/RECORD
