Metadata-Version: 2.1
Name: langgraph_checkpoint_dynamodb
Version: 0.1.0
Summary: DynamoDB Saver for LangGraph Checkpoints
Home-page: https://github.com/justinram11/langgraph-checkpoint-dynamodb
Author: Justin Ramsey
Author-email: justin@rflow.io
Classifier: Programming Language :: Python :: 3
Classifier: Operating System :: OS Independent
Requires-Python: >=3.6
License-File: LICENSE
Requires-Dist: boto3>=1.17.0
Requires-Dist: langchain>=0.3.9
Requires-Dist: langgraph>=0.2.53
